CHANGES.txt
CONTRIBUTORS.txt
MANIFEST.in
README.txt
setup.py
docs/LICENSE.GPL
docs/LICENSE.txt
zettwerk/__init__.py
zettwerk.mobile.egg-info/PKG-INFO
zettwerk.mobile.egg-info/SOURCES.txt
zettwerk.mobile.egg-info/dependency_links.txt
zettwerk.mobile.egg-info/entry_points.txt
zettwerk.mobile.egg-info/namespace_packages.txt
zettwerk.mobile.egg-info/not-zip-safe
zettwerk.mobile.egg-info/requires.txt
zettwerk.mobile.egg-info/top_level.txt
zettwerk/mobile/__init__.py
zettwerk/mobile/configure.zcml
zettwerk/mobile/interfaces.py
zettwerk/mobile/profiles.zcml
zettwerk/mobile/traversal.py
zettwerk/mobile/browser/__init__.py
zettwerk/mobile/browser/configure.zcml
zettwerk/mobile/browser/themes.pt
zettwerk/mobile/browser/themes.py
zettwerk/mobile/locales/de/LC_MESSAGES/zettwerk.mobile.po
zettwerk/mobile/locales/en/LC_MESSAGES/zettwerk.mobile.po
zettwerk/mobile/profiles/default/controlpanel.xml
zettwerk/mobile/profiles/default/metadata.xml
zettwerk/mobile/profiles/default/mobiletheming.xml
zettwerk/mobile/profiles/default/registry.xml
zettwerk/mobile/profiles/default/theme.xml
zettwerk/mobile/static/blank.html
zettwerk/mobile/static/jquery-1.9.1.min.js
zettwerk/mobile/static/manifest.cfg
zettwerk/mobile/static/plone-jquery-mobile.css
zettwerk/mobile/static/rules.xml
zettwerk/mobile/static/jquery.mobile-1.4.2/jquery.mobile-1.4.2.css
zettwerk/mobile/static/jquery.mobile-1.4.2/jquery.mobile-1.4.2.js
zettwerk/mobile/static/jquery.mobile-1.4.2/jquery.mobile-1.4.2.min.css
zettwerk/mobile/static/jquery.mobile-1.4.2/jquery.mobile-1.4.2.min.js
zettwerk/mobile/static/jquery.mobile-1.4.2/jquery.mobile-1.4.2.min.map
zettwerk/mobile/static/jquery.mobile-1.4.2/jquery.mobile.external-png-1.4.2.css
zettwerk/mobile/static/jquery.mobile-1.4.2/jquery.mobile.external-png-1.4.2.min.css
zettwerk/mobile/static/jquery.mobile-1.4.2/jquery.mobile.icons-1.4.2.css
zettwerk/mobile/static/jquery.mobile-1.4.2/jquery.mobile.icons-1.4.2.min.css
zettwerk/mobile/static/jquery.mobile-1.4.2/jquery.mobile.inline-png-1.4.2.css
zettwerk/mobile/static/jquery.mobile-1.4.2/jquery.mobile.inline-png-1.4.2.min.css
zettwerk/mobile/static/jquery.mobile-1.4.2/jquery.mobile.inline-svg-1.4.2.css
zettwerk/mobile/static/jquery.mobile-1.4.2/jquery.mobile.inline-svg-1.4.2.min.css
