Metadata-Version: 1.1
Name: zettwerk.mobile
Version: 0.2.1
Summary: jquery.mobile based themes for plone.
Home-page: http://www.zettwerk.com
Author: Jörg Kubaile / zettwerk GmbH
Author-email: jk@zettwerk.com
License: gpl
Keywords: plone,theme,jquery,jquery.mobile
Platform: UNKNOWN
Classifier: Framework :: Plone
Classifier: Programming Language :: Python
